odoo10_addon_sale_order_restrict_cancel_existing_invoice-10.0.1.0.0.99.dev7-py3.8-nspkg.pth
odoo/addons/sale_order_restrict_cancel_existing_invoice/README.rst
odoo/addons/sale_order_restrict_cancel_existing_invoice/__init__.py
odoo/addons/sale_order_restrict_cancel_existing_invoice/__manifest__.py
odoo/addons/sale_order_restrict_cancel_existing_invoice/i18n/ca.po
odoo/addons/sale_order_restrict_cancel_existing_invoice/i18n/es.po
odoo/addons/sale_order_restrict_cancel_existing_invoice/i18n/sale_order_restrict_cancel_existing_invoice.pot
odoo/addons/sale_order_restrict_cancel_existing_invoice/models/__init__.py
odoo/addons/sale_order_restrict_cancel_existing_invoice/models/sale_order.py
odoo/addons/sale_order_restrict_cancel_existing_invoice/readme/CONTRIBUTORS.rst
odoo/addons/sale_order_restrict_cancel_existing_invoice/readme/DESCRIPTION.rst
odoo/addons/sale_order_restrict_cancel_existing_invoice/readme/USAGE.rst
odoo/addons/sale_order_restrict_cancel_existing_invoice/static/description/icon.png
odoo/addons/sale_order_restrict_cancel_existing_invoice/static/description/index.html
odoo/addons/sale_order_restrict_cancel_existing_invoice/tests/__init__.py
odoo/addons/sale_order_restrict_cancel_existing_invoice/tests/test_sale_cancel_existing_invoice.py
odoo10_addon_sale_order_restrict_cancel_existing_invoice-10.0.1.0.0.99.dev7.dist-info/METADATA
odoo10_addon_sale_order_restrict_cancel_existing_invoice-10.0.1.0.0.99.dev7.dist-info/WHEEL
odoo10_addon_sale_order_restrict_cancel_existing_invoice-10.0.1.0.0.99.dev7.dist-info/namespace_packages.txt
odoo10_addon_sale_order_restrict_cancel_existing_invoice-10.0.1.0.0.99.dev7.dist-info/top_level.txt
odoo10_addon_sale_order_restrict_cancel_existing_invoice-10.0.1.0.0.99.dev7.dist-info/RECORD
